<?xml version="1.0" encoding="utf-8"?>
<doctrine-mapping xmlns="http://doctrine-project.org/schemas/orm/doctrine-mapping" xmlns:xsi="http://www.w3.org/2001/XMLSchema-instance" xsi:schemaLocation="http://doctrine-project.org/schemas/orm/doctrine-mapping http://doctrine-project.org/schemas/orm/doctrine-mapping.xsd">
  <entity name="Symwow\Bundles\DefaultBundle\Entity\RbacAccountPermissions" table="rbac_account_permissions">
    <id name="realmid" type="integer" column="realmId"/>
    <field name="granted" type="boolean" column="granted" nullable="false"/>
    <one-to-one field="permissionid" target-entity="RbacPermissions">
      <join-columns>
        <join-column name="permissionId" referenced-column-name="id"/>
      </join-columns>
    </one-to-one>
    <one-to-one field="accountid" target-entity="Account">
      <join-columns>
        <join-column name="accountId" referenced-column-name="id"/>
      </join-columns>
    </one-to-one>
  </entity>
</doctrine-mapping>
